{"cameraMode":{"drawMode":0,"name":"Shaded","section":"Shading Mode"},"sceneLighting":true,"audioPlay":false,"sceneViewState":{"m_AlwaysRefresh":false,"showFog":true,"showSkybox":true,"showFlares":true,"showImageEffects":true,"showParticleSystems":true,"showVisualEffectGraphs":true,"m_FxEnabled":false},"in2DMode":false,"pivot":{"x":183.40185546875,"y":29.10283660888672,"z":150.42649841308595},"rotation":{"x":-0.20768851041793824,"y":0.7589031457901001,"z":-0.28898584842681887,"w":-0.5455487370491028},"size":0.8660253882408142,"orthographic":false}